afk_bot/__init__.py
afk_bot/cli.py
afk_bot/py.typed
afk_bot/utils.py
afk_bot-0.3.0.dist-info/METADATA
afk_bot-0.3.0.dist-info/WHEEL
afk_bot-0.3.0.dist-info/entry_points.txt
afk_bot-0.3.0.dist-info/licenses/LICENSE
afk_bot-0.3.0.dist-info/RECORD
