Metadata-Version: 2.4
Name: afk-bot
Version: 0.3.0
Summary: A bot for the away from keyboard times
Project-URL: Homepage, https://www.slickml.com
Project-URL: Repository, https://github.com/slickml/afk-bot
Project-URL: Documentation, https://github.com/slickml/afk-bot
Author-email: Amirhessam Tahmassebi <admin@slickml.com>
Maintainer-email: Amirhessam Tahmassebi <admin@slickml.com>
License-Expression: MIT
License-File: LICENSE
Keywords: afk,afk-bot
Classifier: Development Status :: 5 - Production/Stable
Classifier: Intended Audience :: Developers
Classifier: Intended Audience :: Science/Research
Classifier: License :: OSI Approved :: MIT License
Classifier: Natural Language :: English
Classifier: Operating System :: OS Independent
Classifier: Programming Language :: Python :: 3 :: Only
Classifier: Programming Language :: Python :: 3.8
Classifier: Programming Language :: Python :: 3.9
Classifier: Programming Language :: Python :: 3.10
Classifier: Programming Language :: Python :: 3.11
Classifier: Programming Language :: Python :: 3.12
Classifier: Topic :: Software Development :: Libraries :: Python Modules
Classifier: Typing :: Typed
Requires-Python: <3.13,>=3.8
Requires-Dist: pyautogui>=0.9
Requires-Dist: typer>=0.7
